spell_corrector_pt/__init__.py
spell_corrector_pt-0.0.2.dist-info/LICENSE
spell_corrector_pt-0.0.2.dist-info/METADATA
spell_corrector_pt-0.0.2.dist-info/WHEEL
spell_corrector_pt-0.0.2.dist-info/top_level.txt
spell_corrector_pt-0.0.2.dist-info/RECORD
