Metadata-Version: 2.1
Name: spell-corrector-pt
Version: 0.0.2
Summary: This is a simple tool to correct portuguese misspells automatically.
Home-page: https://github.com/samuelhei/spell-corrector-pt
Author: Samuel Heinrichs
Author-email: ti.samuelh@gmail.com
License: UNKNOWN
Platform: UNKNOWN
Classifier: Programming Language :: Python :: 3
Classifier: License :: OSI Approved :: MIT License
Classifier: Operating System :: OS Independent
Requires-Dist: atomicwrites
Requires-Dist: attrs
Requires-Dist: joblib
Requires-Dist: more-itertools
Requires-Dist: numpy
Requires-Dist: pluggy
Requires-Dist: py
Requires-Dist: pytest
Requires-Dist: scikit-learn
Requires-Dist: scipy
Requires-Dist: six
Requires-Dist: sklearn
